geckoboard/__init__.py
geckoboard/api.py
geckoboard/client.py
geckoboard/connection.py
geckoboard/dataset.py
geckoboard/datasets_client.py
geckoboard/response_handler.py
geckoboard.py-1.1.0.dist-info/METADATA
geckoboard.py-1.1.0.dist-info/WHEEL
geckoboard.py-1.1.0.dist-info/top_level.txt
geckoboard.py-1.1.0.dist-info/RECORD
