Metadata-Version: 2.1
Name: geckoboard.py
Version: 1.1.0
Summary: Official Python client for the Geckoboard Datasets API
Home-page: https://github.com/geckoboard/geckoboard-python
Author: Geckoboard
Author-email: dan@geckoboard.com
License: MIT
Keywords: geckoboard,datasets,api,python
Platform: UNKNOWN
Classifier: Development Status :: 5 - Production/Stable
Classifier: Intended Audience :: Developers
Classifier: License :: OSI Approved :: MIT License
Requires-Dist: requests
